invoiceTW/__init__.py
invoiceTW/invoice.py
invoiceTW-0.1.0.dist-info/LICENSE
invoiceTW-0.1.0.dist-info/METADATA
invoiceTW-0.1.0.dist-info/WHEEL
invoiceTW-0.1.0.dist-info/top_level.txt
invoiceTW-0.1.0.dist-info/RECORD
