Metadata-Version: 2.1
Name: invoiceTW
Version: 0.1.0
Summary: Taiwan invoice number
Home-page: https://github.com/tsjeng45/invoiceTW
Author: jeng
Author-email: tsjeng45@yahoo.com.tw
License: UNKNOWN
Keywords: invoice
Platform: UNKNOWN
Classifier: Programming Language :: Python :: 3
Classifier: License :: OSI Approved :: MIT License
